sphinxcontrib_googledrive-0.1.0-py3.7-nspkg.pth
sphinxcontrib/googledrive.py
sphinxcontrib_googledrive-0.1.0.dist-info/LICENSE
sphinxcontrib_googledrive-0.1.0.dist-info/METADATA
sphinxcontrib_googledrive-0.1.0.dist-info/WHEEL
sphinxcontrib_googledrive-0.1.0.dist-info/namespace_packages.txt
sphinxcontrib_googledrive-0.1.0.dist-info/top_level.txt
sphinxcontrib_googledrive-0.1.0.dist-info/RECORD
