Metadata-Version: 2.1
Name: sphinxcontrib-googledrive
Version: 0.1.0
Summary: Sphinx "Google Drive" extension; embed images on Google Drive
Home-page: https://github.com/tk0miya/sphinxcontrib-googledrive/
Author: Takeshi KOMIYA
Author-email: i.tkomiya@gmail.com
License: BSD
Platform: any
Classifier: Development Status :: 4 - Beta
Classifier: Environment :: Console
Classifier: Environment :: Web Environment
Classifier: Framework :: Sphinx :: Extension
Classifier: Intended Audience :: Developers
Classifier: License :: OSI Approved :: BSD License
Classifier: Operating System :: OS Independent
Classifier: Programming Language :: Python
Classifier: Programming Language :: Python :: 3.7
Classifier: Topic :: Documentation
Classifier: Topic :: Documentation :: Sphinx
Classifier: Topic :: Utilities
Requires-Python: >=3.7
Requires-Dist: Sphinx (>=1.8)
Requires-Dist: google-api-python-client
Requires-Dist: pillow
Requires-Dist: python-dateutil
Requires-Dist: requests
